{
  "pagination": {
    "page_number": 1,
    "object_count": 20,
    "page_count": 1,
    "page_size": 50
  },
  "categories": [
    {
      "short_name_localized": "Music",
      "name_localized": "Music",
      "resource_uri": "https://www.eventbriteapi.com/v3/categories/103/",
      "name": "Music",
      "short_name": "Music",
      "id": "103"
    },
    {
      "short_name_localized": "Business",
      "name_localized": "Business & Professional",
      "resource_uri": "https://www.eventbriteapi.com/v3/categories/101/",
      "name": "Business & Professional",
      "short_name": "Business",
      "id": "101"
    },
    {
      "short_name_localized": "Food & Drink",
      "name_localized": "Food & Drink",
      "resource_uri": "https://www.eventbriteapi.com/v3/categories/110/",
      "name": "Food & Drink",
      "short_name": "Food & Drink",
      "id": "110"
    },
    {
      "short_name_localized": "Community",
      "name_localized": "Community & Culture",
      "resource_uri": "https://www.eventbriteapi.com/v3/categories/113/",
      "name": "Community & Culture",
      "short_name": "Community",
      "id": "113"
    },
    {
      "short_name_localized": "Arts",
      "name_localized": "Performing & Visual Arts",
      "resource_uri": "https://www.eventbriteapi.com/v3/categories/105/",
      "name": "Performing & Visual Arts",
      "short_name": "Arts",
      "id": "105"
    },
    {
      "short_name_localized": "Film & Media",
      "name_localized": "Film, Media & Entertainment",
      "resource_uri": "https://www.eventbriteapi.com/v3/categories/104/",
      "name": "Film, Media & Entertainment",
      "short_name": "Film & Media",
      "id": "104"
    },
    {
      "short_name_localized": "Sports & Fitness",
      "name_localized": "Sports & Fitness",
      "resource_uri": "https://www.eventbriteapi.com/v3/categories/108/",
      "name": "Sports & Fitness",
      "short_name": "Sports & Fitness",
      "id": "108"
    },
    {
      "short_name_localized": "Health",
      "name_localized": "Health & Wellness",
      "resource_uri": "https://www.eventbriteapi.com/v3/categories/107/",
      "name": "Health & Wellness",
      "short_name": "Health",
      "id": "107"
    },
    {
      "short_name_localized": "Science & Tech",
      "name_localized": "Science & Technology",
      "resource_uri": "https://www.eventbriteapi.com/v3/categories/102/",
      "name": "Science & Technology",
      "short_name": "Science & Tech",
      "id": "102"
    },
    {
      "short_name_localized": "Travel & Outdoor",
      "name_localized": "Travel & Outdoor",
      "resource_uri": "https://www.eventbriteapi.com/v3/categories/109/",
      "name": "Travel & Outdoor",
      "short_name": "Travel & Outdoor",
      "id": "109"
    },
    {
      "short_name_localized": "Charity & Causes",
      "name_localized": "Charity & Causes",
      "resource_uri": "https://www.eventbriteapi.com/v3/categories/111/",
      "name": "Charity & Causes",
      "short_name": "Charity & Causes",
      "id": "111"
    },
    {
      "short_name_localized": "Spirituality",
      "name_localized": "Religion & Spirituality",
      "resource_uri": "https://www.eventbriteapi.com/v3/categories/114/",
      "name": "Religion & Spirituality",
      "short_name": "Spirituality",
      "id": "114"
    },
    {
      "short_name_localized": "Family & Education",
      "name_localized": "Family & Education",
      "resource_uri": "https://www.eventbriteapi.com/v3/categories/115/",
      "name": "Family & Education",
      "short_name": "Family & Education",
      "id": "115"
    },
    {
      "short_name_localized": "Holiday",
      "name_localized": "Seasonal & Holiday",
      "resource_uri": "https://www.eventbriteapi.com/v3/categories/116/",
      "name": "Seasonal & Holiday",
      "short_name": "Holiday",
      "id": "116"
    },
    {
      "short_name_localized": "Government",
      "name_localized": "Government & Politics",
      "resource_uri": "https://www.eventbriteapi.com/v3/categories/112/",
      "name": "Government & Politics",
      "short_name": "Government",
      "id": "112"
    },
    {
      "short_name_localized": "Fashion",
      "name_localized": "Fashion & Beauty",
      "resource_uri": "https://www.eventbriteapi.com/v3/categories/106/",
      "name": "Fashion & Beauty",
      "short_name": "Fashion",
      "id": "106"
    },
    {
      "short_name_localized": "Home & Lifestyle",
      "name_localized": "Home & Lifestyle",
      "resource_uri": "https://www.eventbriteapi.com/v3/categories/117/",
      "name": "Home & Lifestyle",
      "short_name": "Home & Lifestyle",
      "id": "117"
    },
    {
      "short_name_localized": "Auto, Boat & Air",
      "name_localized": "Auto, Boat & Air",
      "resource_uri": "https://www.eventbriteapi.com/v3/categories/118/",
      "name": "Auto, Boat & Air",
      "short_name": "Auto, Boat & Air",
      "id": "118"
    },
    {
      "short_name_localized": "Hobbies",
      "name_localized": "Hobbies & Special Interest",
      "resource_uri": "https://www.eventbriteapi.com/v3/categories/119/",
      "name": "Hobbies & Special Interest",
      "short_name": "Hobbies",
      "id": "119"
    },
    {
      "short_name_localized": "Other",
      "name_localized": "Other",
      "resource_uri": "https://www.eventbriteapi.com/v3/categories/199/",
      "name": "Other",
      "short_name": "Other",
      "id": "199"
    }
  ],
  "locale": "en_US"
}

